LICENSE
MANIFEST.in
README.md
setup.py
strf/__init__.py
strf.egg-info/PKG-INFO
strf.egg-info/SOURCES.txt
strf.egg-info/dependency_links.txt
strf.egg-info/not-zip-safe
strf.egg-info/pbr.json
strf.egg-info/top_level.txt
tests/__init__.py
tests/test_strf.py