Metadata-Version: 1.1
Name: strf
Version: 0.0.5
Summary: string format locals
Home-page: https://github.com/douglas-larocca/strf
Author: Douglas La Rocca
Author-email: larocca@larocca.io
License: BSD
Keywords: string format locals inspect
Platform: UNKNOWN
Classifier: Development Status :: 2 - Pre-Alpha
Classifier: Intended Audience :: Developers
Classifier: License :: OSI Approved :: BSD License
Classifier: Natural Language :: English
Classifier: Programming Language :: Python :: 3
Classifier: Programming Language :: Python :: 3.3
Classifier: Programming Language :: Python :: 3.4
